mcp_server_vegalite/__init__.py
mcp_server_vegalite/server.py
iflow_mcp_isaacwasserman_mcp_server_vegalite-0.0.1.dist-info/METADATA
iflow_mcp_isaacwasserman_mcp_server_vegalite-0.0.1.dist-info/WHEEL
iflow_mcp_isaacwasserman_mcp_server_vegalite-0.0.1.dist-info/entry_points.txt
iflow_mcp_isaacwasserman_mcp_server_vegalite-0.0.1.dist-info/RECORD
